chn_text_norm/README.md
chn_text_norm/__init__.py
chn_text_norm/basic_class.py
chn_text_norm/basic_constant.py
chn_text_norm/basic_util.py
chn_text_norm/cardinal.py
chn_text_norm/date.py
chn_text_norm/digit.py
chn_text_norm/fraction.py
chn_text_norm/money.py
chn_text_norm/percentage.py
chn_text_norm/telephone.py
chn_text_norm/text.py
chn_text_norm-0.1.1.dist-info/METADATA
chn_text_norm-0.1.1.dist-info/WHEEL
chn_text_norm-0.1.1.dist-info/RECORD
