Metadata-Version: 2.4
Name: chn-text-norm
Version: 0.1.1
Summary: 文本归一化
Project-URL: Homepage, https://example.com/chn-text-norm
Requires-Python: >=3.12
